README.rst
setup.py
lsp/__init__.py
lsp/_buffer.py
lsp/_collector.py
lsp/_connection.py
lsp/_errors.py
lsp/_events.py
lsp/_role.py
lsp/_state.py
lsp/_version.py
lsp.egg-info/PKG-INFO
lsp.egg-info/SOURCES.txt
lsp.egg-info/dependency_links.txt
lsp.egg-info/not-zip-safe
lsp.egg-info/top_level.txt