Metadata-Version: 1.2
Name: lsp
Version: 0.1.1
Summary: Sans-IO pattern, language server protocol implementation
Home-page: https://github.com/WindSoilder/lsp
Author: WindSoilder
Author-email: WindSoilder@outlook.com
License: MIT
Platform: UNKNOWN
Classifier: Development Status :: 3 - Alpha
Classifier: Programming Language :: Python :: 3.6
Classifier: Programming Language :: Python :: 3.7
Classifier: Programming Language :: Python :: 3.8
Classifier: Programming Language :: Python :: Implementation :: CPython
Classifier: Intended Audience :: Developers
Requires-Python: >=3.6
